pycracks/__init__.py
pycracks/__main__.py
pycracks/logger.py
pycracks/py.typed
pycracks/pycracks.py
pycracks-0.21.0.dist-info/LICENSE
pycracks-0.21.0.dist-info/METADATA
pycracks-0.21.0.dist-info/WHEEL
pycracks-0.21.0.dist-info/entry_points.txt
pycracks-0.21.0.dist-info/top_level.txt
pycracks-0.21.0.dist-info/RECORD
