Metadata-Version: 2.1
Name: pycracks
Version: 0.21.0
Author-email: "Ezequiel L. Castaño" <castanoezequielleonardo@gmail.com>
License: MIT
Project-URL: homepage, https://github.com/elc/pycracks
Project-URL: documentation, https://github.com/elc/pycracks
Project-URL: repository, https://github.com/elc/pycracks
Project-URL: changelog, https://github.com/ELC/pycracks/blob/master/CHANGELOG.md
Classifier: Development Status :: 4 - Beta
Classifier: Programming Language :: Python
Classifier: License :: OSI Approved :: MIT License
Classifier: Intended Audience :: Developers
Classifier: Framework :: Hypothesis
Classifier: Framework :: Pytest
Classifier: Environment :: Console
Classifier: Natural Language :: English
Classifier: Operating System :: OS Independent
Classifier: Topic :: Software Development :: Quality Assurance
Classifier: Topic :: Software Development :: Testing
Classifier: Topic :: Software Development :: Version Control :: Git
Classifier: Typing :: Typed
Requires-Python: >=3.9
License-File: LICENSE
Requires-Dist: gitpython
Requires-Dist: packaging
Requires-Dist: typer
Requires-Dist: typing-extensions
